ect/__init__.py
ect/dect.py
ect/directions.py
ect/ect.py
ect/embed_complex.py
ect/results.py
ect/sect.py
ect/utils/examples.py
ect/utils/face_check.py
ect/utils/naming.py
ect/validation/__init__.py
ect/validation/base.py
ect/validation/rules.py
ect/validation/validator.py
ect-1.2.2.dist-info/licenses/LICENSE
ect-1.2.2.dist-info/METADATA
ect-1.2.2.dist-info/WHEEL
ect-1.2.2.dist-info/top_level.txt
ect-1.2.2.dist-info/RECORD
