Metadata-Version: 2.4
Name: ect
Version: 1.2.2
Summary: A python package for computing the Euler Characteristic Transform
Author-email: Liz Munch <muncheli@msu.edu>
Project-URL: Homepage, https://munchlab.github.io/ect
Project-URL: Repository, https://github.com/MunchLab/ect
Project-URL: Issues, https://github.com/MunchLab/ect/issues
Classifier: Programming Language :: Python :: 3
Classifier: License :: OSI Approved :: GNU General Public License v3 (GPLv3)
Classifier: Operating System :: OS Independent
Requires-Python: >=3.10
License-File: LICENSE
Requires-Dist: numpy
Requires-Dist: networkx
Requires-Dist: matplotlib
Requires-Dist: numba
Requires-Dist: scipy
Requires-Dist: scikit-learn
Dynamic: license-file
